{
	"name": "payments_dataset",
	"properties": {
		"linkedServiceName": {
			"referenceName": "AzureBlobStorage1",
			"type": "LinkedServiceReference"
		},
		"folder": {
			"name": "source_datasets"
		},
		"annotations": [],
		"type": "DelimitedText",
		"typeProperties": {
			"location": {
				"type": "AzureBlobStorageLocation",
				"fileName": "payments.csv",
				"folderPath": "retailsamples",
				"container": "input"
			},
			"columnDelimiter": ",",
			"escapeChar": "\\",
			"firstRowAsHeader": true,
			"quoteChar": "\""
		},
		"schema": [
			{
				"name": "payment_id",
				"type": "String"
			},
			{
				"name": "order_id",
				"type": "String"
			},
			{
				"name": "amount",
				"type": "String"
			},
			{
				"name": "payment_method",
				"type": "String"
			},
			{
				"name": "status",
				"type": "String"
			}
		]
	},
	"type": "Microsoft.DataFactory/factories/datasets"
}